tsccm/__about__.py
tsccm/__init__.py
tsccm/__main__.py
tsccm/_version.py
tsccm/utilities.py
tsccm/modules/__init__.py
tsccm/modules/tscapi/__init__.py
tsccm-0.0.6.dist-info/licenses/LICENSE
tsccm-0.0.6.dist-info/METADATA
tsccm-0.0.6.dist-info/WHEEL
tsccm-0.0.6.dist-info/entry_points.txt
tsccm-0.0.6.dist-info/top_level.txt
tsccm-0.0.6.dist-info/RECORD
