Metadata-Version: 2.4
Name: tsccm
Version: 0.0.6
Summary: TSCCM (Tenable.SC CLI Manager) by LimberDuck
Home-page: https://github.com/LimberDuck/tsccm
Author: Damian Krawczyk
Author-email: damian.krawczyk@limberduck.org
Classifier: Programming Language :: Python :: 3.13
Classifier: Programming Language :: Python :: 3.12
Classifier: Programming Language :: Python :: 3.11
Classifier: Programming Language :: Python :: 3.10
Classifier: License :: OSI Approved :: MIT License
Classifier: Operating System :: OS Independent
Classifier: Development Status :: 4 - Beta
Classifier: Environment :: Console
License-File: LICENSE
Requires-Dist: certstore>=0.0.2
Requires-Dist: click>=8.2.1
Requires-Dist: keyring>=25.6.0
Requires-Dist: pyTenable>=1.8.3
Requires-Dist: oauthlib>=3.3.1
Requires-Dist: pandas>=2.3.2
Requires-Dist: tabulate>=0.9.0
Requires-Dist: requests>=2.32.5
Requires-Dist: packaging>=25.0
Dynamic: author
Dynamic: author-email
Dynamic: classifier
Dynamic: description
Dynamic: description-content-type
Dynamic: home-page
Dynamic: license-file
Dynamic: requires-dist
Dynamic: summary
